CHANGELOG.rst
LICENSE.txt
MANIFEST.in
README.rst
setup.py
django_publicmanager/__init__.py
django_publicmanager/managers.py
django_publicmanager/models.py
django_publicmanager/queryset.py
django_publicmanager.egg-info/PKG-INFO
django_publicmanager.egg-info/SOURCES.txt
django_publicmanager.egg-info/dependency_links.txt
django_publicmanager.egg-info/requires.txt
django_publicmanager.egg-info/top_level.txt