Metadata-Version: 1.0
Name: django-publicmanager
Version: 0.9.2
Summary: Custom managers that handle public availability of database objects.
Home-page: https://github.com/gregor-muellegger/django-publicmanager
Author: Gregor Müllegger
Author-email: gregor@muellegger.de
License: BSD
Platform: UNKNOWN
Classifier: Development Status :: 5 - Production/Stable
Classifier: Environment :: Web Environment
Classifier: Framework :: Django
Classifier: Intended Audience :: Developers
Classifier: License :: OSI Approved :: BSD License
Classifier: Natural Language :: English
Classifier: Operating System :: OS Independent
Classifier: Programming Language :: Python
